skia_gradient_array/__init__.py
skia_gradient_array/_version.py
skia_gradient_array/example.py
skia_gradient_array/gradient_canvas.py
skia_gradient_array/gradient_param.py
skia_gradient_array/set_patch_background.py
skia_gradient_array/ui_gradient.py
skia_gradient_array/data/ui-gradients.json
skia_gradient_array/tests/__init__.py
skia_gradient_array/tests/test_example.py
skia_gradient_array-0.1.0.dist-info/LICENSE
skia_gradient_array-0.1.0.dist-info/METADATA
skia_gradient_array-0.1.0.dist-info/WHEEL
skia_gradient_array-0.1.0.dist-info/top_level.txt
skia_gradient_array-0.1.0.dist-info/RECORD
